fexact.cpython-39-darwin.so
fexact-0.1.0.dist-info/LICENSE.txt
fexact-0.1.0.dist-info/METADATA
fexact-0.1.0.dist-info/WHEEL
fexact-0.1.0.dist-info/top_level.txt
fexact-0.1.0.dist-info/RECORD
