Metadata-Version: 1.0
Name: fexact
Version: 0.1.0
Summary: Exact Fisher test for nxm contingency matrix based on fortran acm 643 and R
Home-page: https://github.com/boussoffara/fexact
Author: boussoffara@me.com
Author-email: boussoffara@me.com
License: GPLv3
Platform: UNKNOWN
